{
    "appKeys": {},
    "capabilities": [
        ""
    ],
    "companyName": "arturas@smorgun.lt",
    "longName": "PebbleDo",
    "projectType": "pebblejs",
    "resources": {
        "media": [
            {
                "file": "images/menu_icon.png",
                "menuIcon": true,
                "name": "IMAGE_MENU_ICON",
                "type": "png"
            },
            {
                "file": "images/logo_splash.png",
                "name": "IMAGE_LOGO_SPLASH",
                "type": "png"
            },
            {
                "file": "images/tile_splash.png",
                "name": "IMAGE_TILE_SPLASH",
                "type": "png"
            },
            {
                "file": "fonts/UbuntuMono-Regular.ttf",
                "name": "MONO_FONT_14",
                "type": "font"
            }
        ]
    },
    "sdkVersion": "3",
    "shortName": "PebbleDo",
    "uuid": "67d56d76-45ae-4f52-91f8-cc4f951c6bfe",
    "versionCode": 1,
    "versionLabel": "1.1",
    "watchapp": {
        "watchface": false
    }
}
